shellui/__init__.py
shellui/core/__init__.py
shellui/core/handler.py
shellui/core/interfaces.py
shellui/core/terminal.py
shellui/core/typings.py
shellui/ui/__init__.py
shellui/ui/abstracts.py
shellui/ui/board.py
shellui/ui/root.py
shellui-0.3.0.post1.dist-info/LICENSE
shellui-0.3.0.post1.dist-info/METADATA
shellui-0.3.0.post1.dist-info/WHEEL
shellui-0.3.0.post1.dist-info/top_level.txt
shellui-0.3.0.post1.dist-info/RECORD
