Metadata-Version: 2.1
Name: shellui
Version: 0.3.0.post1
Summary: library simplifies the creation of TUI (Text User Interface) in the terminal. Offers a clean and intuitive architecture to help you build interactive applications effortlessly.
Home-page: https://github.com/highofolly/shellui
Author: highofolly
Author-email: sw3atyspace@email.com
License: MIT
Classifier: Programming Language :: Python :: 3.12
Classifier: License :: OSI Approved :: MIT License
Classifier: Operating System :: OS Independent
Requires-Python: >=3.12
License-File: LICENSE
Requires-Dist: windows-curses>=2.3.3
